f_durand_tests_github_actions/__init__.py
f_durand_tests_github_actions/f_durand_tests_github_actions.py
f_durand_tests_github_actions/SubPackage1/MyClass1.py
f_durand_tests_github_actions/SubPackage1/__init__.py
f_durand_tests_github_actions/SubPackage2/MyClass2.py
f_durand_tests_github_actions/SubPackage2/MyClass3.py
f_durand_tests_github_actions/SubPackage2/__init__.py
tests/__init__.py
tests/test_f_durand_tests_github_actions.py
f_durand_tests_github_actions-0.1.0.dist-info/AUTHORS.rst
f_durand_tests_github_actions-0.1.0.dist-info/LICENSE
f_durand_tests_github_actions-0.1.0.dist-info/METADATA
f_durand_tests_github_actions-0.1.0.dist-info/WHEEL
f_durand_tests_github_actions-0.1.0.dist-info/top_level.txt
f_durand_tests_github_actions-0.1.0.dist-info/RECORD
