Metadata-Version: 2.1
Name: f-durand-tests-github-actions
Version: 0.1.0
Summary: This is a test of GitHub actions.
Home-page: https://github.com/francois-durand/f_durand_tests_github_actions
Author: François Durand
Author-email: fradurand@gmail.com
License: GNU General Public License v3
Keywords: f_durand_tests_github_actions
Platform: UNKNOWN
Classifier: Development Status :: 2 - Pre-Alpha
Classifier: Intended Audience :: Developers
Classifier: License :: OSI Approved :: GNU General Public License v3 (GPLv3)
Classifier: Natural Language :: English
Classifier: Programming Language :: Python :: 3
Classifier: Programming Language :: Python :: 3.6
Classifier: Programming Language :: Python :: 3.7
Classifier: Programming Language :: Python :: 3.8
Requires-Python: >=3.6
